GDALToolBox/__init__.py
GDALToolBox/gdaltools.py
OSToolBox/__init__.py
OSToolBox/tools.py
OSToolBox-1.8.2.dist-info/METADATA
OSToolBox-1.8.2.dist-info/WHEEL
OSToolBox-1.8.2.dist-info/top_level.txt
OSToolBox-1.8.2.dist-info/RECORD
