Metadata-Version: 2.1
Name: OSToolBox
Version: 1.8.2
Summary: implement many basic function and tools for GIS, Point clouds and General coding with python
Home-page: https://github.com/NanBlanc/OSToolBox
Author: Olivier Stocker
Author-email: stocker.olivier@gmail.com
License: MIT
Requires-Dist: numpy
Requires-Dist: matplotlib
Requires-Dist: scikit-learn
